{
  "gitSyncId": "6a0eb4c70281dcff620d4402_9c798ed5-6da8-457b-bcb4-26e5e5ae8550",
  "id": "Login_Page_getBookedCollections",
  "pluginId": "postgres-plugin",
  "pluginType": "DB",
  "unpublishedAction": {
    "actionConfiguration": {
      "body": "SELECT *\nFROM collections\nWHERE status = 'BOOKED'\nORDER BY collectiondate DESC;\n",
      "encodeParamsToggle": true,
      "paginationType": "NONE",
      "pluginSpecifiedTemplates": [
        {
          "value": true
        }
      ],
      "timeoutInMillisecond": 10000
    },
    "confirmBeforeExecute": false,
    "datasource": {
      "id": "ERP_DB",
      "isAutoGenerated": false,
      "name": "ERP_DB",
      "pluginId": "postgres-plugin"
    },
    "dynamicBindingPathList": [],
    "name": "getBookedCollections",
    "pageId": "Login_Page",
    "runBehaviour": "MANUAL",
    "userSetOnLoad": false
  }
}