{
  "gitSyncId": "6a27f57e40e83311173efe61_d5b18857-42ed-49f4-bf5f-d4ee8db57cc0",
  "id": "Asset_Page_BlanccoParser.cleanValue",
  "pluginId": "js-plugin",
  "pluginType": "JS",
  "unpublishedAction": {
    "actionConfiguration": {
      "encodeParamsToggle": true,
      "jsArguments": [
        {
          "name": "value"
        }
      ],
      "paginationType": "NONE",
      "timeoutInMillisecond": 10000
    },
    "collectionId": "Asset_Page_BlanccoParser",
    "confirmBeforeExecute": false,
    "datasource": {
      "isAutoGenerated": false,
      "name": "UNUSED_DATASOURCE",
      "pluginId": "js-plugin"
    },
    "dynamicBindingPathList": [
      {
        "key": "body"
      }
    ],
    "fullyQualifiedName": "BlanccoParser.cleanValue",
    "name": "cleanValue",
    "pageId": "Asset_Page",
    "runBehaviour": "MANUAL",
    "userSetOnLoad": false
  }
}