{
  "gitSyncId": "6a305b9e0882adc7e482e226_b86cd9fd-ac59-4131-88de-c4423eb3ead6",
  "id": "Asset_Page_qry_get_parts_stock",
  "pluginId": "postgres-plugin",
  "pluginType": "DB",
  "unpublishedAction": {
    "actionConfiguration": {
      "body": "SELECT\n  hp.id,\n  hp.part_ref,\n  pt.name AS part_type,\n  hp.spec,\n  hp.serial_number,\n  hp.condition_grade,\n  hp.status,\n  hp.removed_at::date AS in_stock_since,\n  hp.disposition_due,\n  a.asset_ref AS source_asset_ref,\n  CASE \n    WHEN hp.disposition_due < CURRENT_DATE THEN true \n    ELSE false \n  END AS is_overdue\nFROM harvested_parts hp\nLEFT JOIN part_types pt ON pt.part_type_id = hp.part_type_id\nLEFT JOIN assets a ON a.asset_id = hp.source_asset_id\nWHERE hp.status = 'IN_STOCK'\nAND hp.source_asset_id != {{appsmith.URL.queryParams.asset_id}}\nAND (\n  '{{appsmith.store.stock_type_filter}}' = '' \n  OR pt.name = '{{appsmith.store.stock_type_filter}}'\n)\nAND (\n  '{{appsmith.store.stock_grade_filter}}' = '' \n  OR POSITION(hp.condition_grade IN '{{appsmith.store.stock_grade_filter}}') > 0\n)\nORDER BY hp.removed_at ASC;",
      "encodeParamsToggle": true,
      "paginationType": "NONE",
      "pluginSpecifiedTemplates": [
        {
          "value": false
        }
      ],
      "timeoutInMillisecond": 10000
    },
    "confirmBeforeExecute": false,
    "datasource": {
      "id": "ERP_DB",
      "isAutoGenerated": false,
      "name": "ERP_DB",
      "pluginId": "postgres-plugin"
    },
    "dynamicBindingPathList": [
      {
        "key": "body"
      }
    ],
    "name": "qry_get_parts_stock",
    "pageId": "Asset_Page",
    "runBehaviour": "AUTOMATIC",
    "userSetOnLoad": false
  }
}