{
  "animateLoading": true,
  "borderRadius": "{{appsmith.theme.borderRadius.appBorderRadius}}",
  "bottomRow": 5,
  "boxShadow": "0 1px 3px 0 rgba(0, 0, 0, 0.1), 0 1px 2px 0 rgba(0, 0, 0, 0.06)",
  "buttonColor": "#f5f3ff",
  "buttonVariant": "PRIMARY",
  "dynamicBindingPathList": [
    {
      "key": "borderRadius"
    }
  ],
  "dynamicTriggerPathList": [],
  "iconName": "shield",
  "isDisabled": false,
  "isLoading": false,
  "isVisible": true,
  "key": "pp6m5wyi40",
  "leftColumn": 3,
  "minWidth": 50,
  "mobileBottomRow": 5,
  "mobileLeftColumn": 4,
  "mobileRightColumn": 8,
  "mobileTopRow": 1,
  "needsErrorInfo": false,
  "parentColumnSpace": 7.736328125,
  "parentId": "up2tqgbbn4",
  "parentRowSpace": 10,
  "renderMode": "CANVAS",
  "responsiveBehavior": "hug",
  "rightColumn": 7,
  "topRow": 1,
  "type": "ICON_BUTTON_WIDGET",
  "version": 1,
  "widgetId": "c3q50ea3l0",
  "widgetName": "IconButton1Copy"
}