{
  "gitSyncId": "6a27f57e40e83311173efe61_d84a788e-f248-48e5-a2a0-c5b39e5ea22a",
  "id": "Asset_Page_TextFormat.upperCase",
  "pluginId": "js-plugin",
  "pluginType": "JS",
  "unpublishedAction": {
    "actionConfiguration": {
      "encodeParamsToggle": true,
      "jsArguments": [
        {
          "name": "value",
          "value": ""
        }
      ],
      "paginationType": "NONE",
      "timeoutInMillisecond": 10000
    },
    "collectionId": "Asset_Page_TextFormat",
    "confirmBeforeExecute": false,
    "datasource": {
      "isAutoGenerated": false,
      "name": "UNUSED_DATASOURCE",
      "pluginId": "js-plugin"
    },
    "dynamicBindingPathList": [
      {
        "key": "body"
      }
    ],
    "fullyQualifiedName": "TextFormat.upperCase",
    "name": "upperCase",
    "pageId": "Asset_Page",
    "runBehaviour": "MANUAL",
    "userSetOnLoad": false
  }
}